audioevaluator/__init__.py
audioevaluator/evaluator.py
audio_evaluator-1.0.6.dist-info/LICENSE.txt
audio_evaluator-1.0.6.dist-info/METADATA
audio_evaluator-1.0.6.dist-info/WHEEL
audio_evaluator-1.0.6.dist-info/top_level.txt
audio_evaluator-1.0.6.dist-info/RECORD
